LICENSE
README.md
setup.cfg
setup.py
SeCreepy.egg-info/PKG-INFO
SeCreepy.egg-info/SOURCES.txt
SeCreepy.egg-info/dependency_links.txt
SeCreepy.egg-info/requires.txt
SeCreepy.egg-info/top_level.txt
secreepy/__init__.py
secreepy/config.py
secreepy/decorators.py
secreepy/exceptions.py
secreepy/html.py
secreepy/logger.py
secreepy/utils.py
secreepy/web.py
secreepy/drivers/__init__.py
secreepy/drivers/chrome_driver.py
secreepy/drivers/driver.py
secreepy/drivers/firefox_driver.py
secreepy/drivers/undetected_chrome_driver.py